jaxonmodels/__init__.py
jaxonmodels/functions/__init__.py
jaxonmodels/functions/attention.py
jaxonmodels/functions/bpe_simple_vocab_16e6.txt.gz
jaxonmodels/functions/initialization.py
jaxonmodels/functions/masking.py
jaxonmodels/functions/normalization.py
jaxonmodels/functions/regularization.py
jaxonmodels/functions/state_space.py
jaxonmodels/functions/text.py
jaxonmodels/functions/utils.py
jaxonmodels/layers/__init__.py
jaxonmodels/layers/abstract.py
jaxonmodels/layers/attention.py
jaxonmodels/layers/convolution.py
jaxonmodels/layers/normalization.py
jaxonmodels/layers/regularization.py
jaxonmodels/layers/sequential.py
jaxonmodels/layers/state_space.py
jaxonmodels/models/__init__.py
jaxonmodels/models/alexnet.py
jaxonmodels/models/clip.py
jaxonmodels/models/convnext.py
jaxonmodels/models/efficientnet.py
jaxonmodels/models/gemma.py
jaxonmodels/models/mamba.py
jaxonmodels/models/resnet.py
jaxonmodels/models/sam.py
jaxonmodels/models/siglib.py
jaxonmodels/models/swin_transformer.py
jaxonmodels/models/vit.py
jaxonmodels/statedict2pytree/__init__.py
jaxonmodels/statedict2pytree/model_orders.py
jaxonmodels/statedict2pytree/s2p.py
jaxonmodels-0.2.1.dist-info/METADATA
jaxonmodels-0.2.1.dist-info/WHEEL
jaxonmodels-0.2.1.dist-info/licenses/LICENSE
jaxonmodels-0.2.1.dist-info/RECORD
