Metadata-Version: 2.4
Name: jaxonmodels
Version: 0.2.1
Summary: JAX models for deep learning
Author-email: "Artur A. Galstyan" <mail@arturgalstyan.dev>
License: MIT License
License-File: LICENSE
Requires-Python: ~=3.10
Requires-Dist: beartype
Requires-Dist: equinox
Requires-Dist: ftfy
Requires-Dist: grain
Requires-Dist: jax
Requires-Dist: jaxlib
Requires-Dist: jaxonloader
Requires-Dist: jaxtyping
Requires-Dist: loguru
Requires-Dist: numpy
Requires-Dist: optax
Requires-Dist: pydantic
Requires-Dist: pytest
Requires-Dist: regex
Requires-Dist: tqdm
Requires-Dist: typing-extensions
Provides-Extra: dev
Requires-Dist: mkdocs; extra == 'dev'
Requires-Dist: pre-commit; extra == 'dev'
Requires-Dist: pytest; extra == 'dev'
Provides-Extra: examples
Requires-Dist: clu; extra == 'examples'
Requires-Dist: requests; extra == 'examples'
Requires-Dist: tensorflow-cpu; extra == 'examples'
Requires-Dist: tensorflow-datasets; extra == 'examples'
Provides-Extra: tests
Requires-Dist: torch; extra == 'tests'
Requires-Dist: torchvision; extra == 'tests'
